aapns/__init__.py
aapns/api.py
aapns/cli.py
aapns/config.py
aapns/connection.py
aapns/errors.py
aapns/models.py
aapns/pool.py
aapns/py.typed
aapns-23.7.dist-info/LICENSE
aapns-23.7.dist-info/METADATA
aapns-23.7.dist-info/WHEEL
aapns-23.7.dist-info/entry_points.txt
aapns-23.7.dist-info/RECORD
