Metadata-Version: 2.1
Name: aapns
Version: 23.7
Summary: Asynchronous Apple Push Notification Service Client
Home-page: https://github.com/HENNGE/aapns
License: Apache-2.0
Keywords: push-notification,apple,ios,asyncio
Author: Jonas Obrist
Author-email: jonas.obrist@hennge.com
Requires-Python: >=3.8,<4.0
Classifier: Development Status :: 5 - Production/Stable
Classifier: Framework :: AsyncIO
Classifier: Intended Audience :: Developers
Classifier: License :: OSI Approved :: Apache Software License
Classifier: Operating System :: MacOS :: MacOS X
Classifier: Operating System :: OS Independent
Classifier: Operating System :: POSIX
Classifier: Operating System :: POSIX :: Linux
Classifier: Programming Language :: Python :: 3
Classifier: Programming Language :: Python :: 3.8
Classifier: Programming Language :: Python :: 3.9
Classifier: Programming Language :: Python :: 3.10
Classifier: Programming Language :: Python :: 3.11
Classifier: Programming Language :: Python :: 3 :: Only
Classifier: Topic :: Communications
Classifier: Typing :: Typed
Provides-Extra: cli
Requires-Dist: attrs (>=23,<24)
Requires-Dist: click (>=8,<9) ; extra == "cli"
Requires-Dist: h2 (>=3.2.0,<4.0.0)
Project-URL: Documentation, https://aapns.readthedocs.io
Project-URL: Repository, https://github.com/hennge/aapns
